{"vlfeat": [[41530, 3, 2]], "document": [[41530, 5, 1]], "c": [[41530, 354, 2]], "api": [[41530, 4, 2]], "org": [[41530, 1, 2]], "home": [[41530, 1, 1], [41536, 2, 1]], "about": [[41530, 1, 1], [41536, 3, 1]], "licens": [[41530, 1, 1]], "download": [[41530, 1, 1]], "use": [[41530, 4, 1], [41536, 3, 1]], "from": [[41530, 4, 1], [41532, 1, 1], [41536, 5, 1]], "matlab": [[41530, 2, 1]], "octav": [[41530, 1, 1]], "the": [[41530, 3, 1], [41536, 48, 2], [41539, 1, 1]], "command": [[41530, 1, 1]], "line": [[41530, 1, 1]], "xcode": [[41530, 1, 1]], "visual": [[41530, 1, 1]], "g": [[41530, 2, 1]], "compil": [[41530, 3, 1], [41536, 1, 1]], "on": [[41530, 2, 1], [41535, 1, 1], [41536, 9, 2]], "unix": [[41530, 1, 1]], "like": [[41530, 1, 1]], "platform": [[41530, 1, 1]], "window": [[41530, 1, 1]], "tutori": [[41530, 1, 1]], "local": [[41530, 2, 1]], "featur": [[41530, 4, 1]], "frame": [[41530, 1, 1]], "covari": [[41530, 1, 1]], "detector": [[41530, 3, 1]], "hog": [[41530, 28, 1]], "sift": [[41530, 41, 1]], "and": [[41530, 5, 1], [41532, 1, 1], [41536, 32, 2], [41537, 2, 2], [41538, 1, 1], [41539, 1, 1]], "descriptor": [[41530, 2, 1]], "dens": [[41530, 1, 1]], "liop": [[41530, 21, 1]], "mser": [[41530, 29, 1]], "distanc": [[41530, 1, 1]], "transform": [[41530, 1, 1]], "fisher": [[41530, 7, 1]], "vector": [[41530, 2, 1]], "vlad": [[41530, 7, 1]], "gaussian": [[41530, 1, 1]], "mixtur": [[41530, 1, 1]], "model": [[41530, 1, 1], [41536, 1, 1]], "k": [[41530, 3, 1]], "mean": [[41530, 3, 1]], "cluster": [[41530, 1, 1]], "agglom": [[41530, 1, 1]], "infrom": [[41530, 1, 1]], "bottleneck": [[41530, 1, 1]], "quick": [[41530, 1, 1]], "shift": [[41530, 1, 1]], "superpixel": [[41530, 2, 1]], "slic": [[41530, 3, 1]], "support": [[41530, 1, 1], [41536, 5, 1]], "machin": [[41530, 1, 1]], "svm": [[41530, 129, 1]], "kd": [[41530, 1, 1]], "tree": [[41530, 1, 1]], "forest": [[41530, 1, 1]], "plot": [[41530, 1, 1]], "ap": [[41530, 1, 1]], "roc": [[41530, 1, 1]], "curv": [[41530, 1, 1]], "miscellan": [[41530, 1, 1]], "util": [[41530, 1, 1]], "integ": [[41530, 2, 1]], "hierarch": [[41530, 1, 1]], "applic": [[41530, 1, 1], [41536, 1, 1]], "man": [[41530, 1, 1]], "page": [[41530, 3, 1]], "main": [[41530, 1, 1]], "relat": [[41530, 1, 1]], "data": [[41530, 1, 1]], "structur": [[41530, 1, 1]], "file": [[41530, 2, 1]], "list": [[41530, 2, 1]], "global": [[41530, 1, 1], [41536, 2, 1]], "all": [[41530, 2, 1], [41536, 1, 1]], "function": [[41530, 2, 1]], "variabl": [[41530, 2, 1]], "typedef": [[41530, 2, 1]], "enumer": [[41530, 2, 1]], "macro": [[41530, 1, 1]], "_": [[41530, 1, 1]], "a": [[41530, 2, 1], [41535, 1, 1], [41536, 21, 2]], "d": [[41530, 1, 1]], "e": [[41530, 1, 1]], "f": [[41530, 1, 1], [41532, 1, 1], [41534, 1, 1]], "h": [[41530, 733, 1]], "i": [[41530, 1, 1]], "n": [[41530, 1, 1]], "o": [[41530, 1, 1]], "p": [[41530, 1, 1]], "r": [[41530, 1, 1]], "u": [[41530, 1, 1]], "v": [[41530, 2, 2]], "x": [[41530, 1, 1]], "here": [[41530, 1, 1], [41536, 2, 1]], "is": [[41530, 1, 1], [41536, 9, 1]], "of": [[41530, 2, 1], [41533, 2, 2], [41536, 31, 2]], "defin": [[41530, 1, 1]], "enum": [[41530, 1, 1]], "with": [[41530, 1, 1], [41536, 9, 1]], "link": [[41530, 1, 1]], "to": [[41530, 1, 1], [41536, 13, 1]], "vl_abs_d": [[41530, 1, 1]], "mathop": [[41530, 62, 1]], "vl_abs_f": [[41530, 1, 1]], "vl_aib_calculate_inform": [[41530, 1, 1]], "aib": [[41530, 18, 1]], "vl_aib_delet": [[41530, 1, 1]], "vl_aib_get_cost": [[41530, 1, 1]], "vl_aib_get_par": [[41530, 1, 1]], "vl_aib_get_verbos": [[41530, 1, 1]], "vl_aib_merge_nod": [[41530, 1, 1]], "vl_aib_min_beta": [[41530, 1, 1]], "vl_aib_new": [[41530, 1, 1]], "vl_aib_new_nodelist": [[41530, 1, 1]], "vl_aib_new_pc": [[41530, 1, 1]], "vl_aib_new_px": [[41530, 1, 1]], "vl_aib_normalize_p": [[41530, 1, 1]], "vl_aib_process": [[41530, 1, 1]], "vl_aib_set_verbos": [[41530, 1, 1]], "vl_aib_update_beta": [[41530, 1, 1]], "vl_arch_big_endian": [[41530, 1, 1]], "host": [[41530, 73, 1], [41536, 1, 1]], "vl_arch_ia64": [[41530, 1, 1]], "vl_arch_ix86": [[41530, 1, 1]], "vl_arch_little_endian": [[41530, 1, 1]], "vl_array_dealloc": [[41530, 1, 1]], "array": [[41530, 16, 1]], "vl_array_delet": [[41530, 1, 1]], "vl_array_get_data": [[41530, 1, 1]], "vl_array_get_data_typ": [[41530, 1, 1]], "vl_array_get_dimens": [[41530, 1, 1]], "vl_array_get_num_dimens": [[41530, 1, 1]], "vl_array_get_num_el": [[41530, 1, 1]], "vl_array_init": [[41530, 1, 1]], "vl_array_init_envelop": [[41530, 1, 1]], "vl_array_init_matrix": [[41530, 1, 1]], "vl_array_init_matrix_envelop": [[41530, 1, 1]], "vl_array_max_num_dimens": [[41530, 1, 1]], "vl_array_new": [[41530, 1, 1]], "vl_array_new_envelop": [[41530, 1, 1]], "vl_array_new_matrix": [[41530, 1, 1]], "vl_array_new_matrix_envelop": [[41530, 1, 1]], "vl_big_int": [[41530, 1, 1]], "vl_big_uint": [[41530, 1, 1]], "vl_bool": [[41530, 1, 1]], "vl_calloc": [[41530, 1, 1]], "gener": [[41530, 84, 1]], "vl_cat": [[41530, 1, 1]], "vl_ceil_d": [[41530, 1, 1]], "vl_ceil_f": [[41530, 1, 1]], "vl_compiler_gnuc": [[41530, 1, 1]], "vl_compiler_ilp32": [[41530, 1, 1]], "vl_compiler_lcc": [[41530, 1, 1]], "vl_compiler_llp64": [[41530, 1, 1]], "vl_compiler_lp64": [[41530, 1, 1]], "vl_compiler_msc": [[41530, 1, 1]], "vl_configuration_to_string_copi": [[41530, 1, 1]], "vl_constructor": [[41530, 1, 1]], "vl_covdet_append_featur": [[41530, 1, 1]], "covdet": [[41530, 88, 1]], "vl_covdet_delet": [[41530, 1, 1]], "vl_covdet_detect": [[41530, 1, 1]], "vl_covdet_drop_features_outsid": [[41530, 1, 1]], "vl_covdet_extract_affine_shap": [[41530, 1, 1]], "vl_covdet_extract_affine_shape_for_fram": [[41530, 1, 1]], "vl_covdet_extract_laplacian_scal": [[41530, 1, 1]], "vl_covdet_extract_laplacian_scales_for_fram": [[41530, 1, 1]], "vl_covdet_extract_orient": [[41530, 1, 1]], "vl_covdet_extract_orientations_for_fram": [[41530, 1, 1]], "vl_covdet_extract_patch_for_fram": [[41530, 1, 1]], "vl_covdet_extract_patch_help": [[41530, 1, 1]], "vl_covdet_get_aa_accurate_smooth": [[41530, 1, 1]], "vl_covdet_get_css": [[41530, 1, 1]], "vl_covdet_get_edge_threshold": [[41530, 1, 1]], "vl_covdet_get_featur": [[41530, 1, 1]], "vl_covdet_get_first_octav": [[41530, 1, 1]], "vl_covdet_get_gss": [[41530, 1, 1]], "vl_covdet_get_laplacian_peak_threshold": [[41530, 1, 1]], "vl_covdet_get_laplacian_scales_statist": [[41530, 1, 1]], "vl_covdet_get_non_extrema_suppression_threshold": [[41530, 1, 1]], "vl_covdet_get_num_featur": [[41530, 1, 1]], "vl_covdet_get_num_non_extrema_suppress": [[41530, 1, 1]], "vl_covdet_get_octave_resolut": [[41530, 1, 1]], "vl_covdet_get_peak_threshold": [[41530, 1, 1]], "vl_covdet_get_transpos": [[41530, 1, 1]], "vl_covdet_new": [[41530, 1, 1]], "vl_covdet_put_imag": [[41530, 1, 1]], "vl_covdet_reset": [[41530, 1, 1]], "vl_covdet_set_aa_accurate_smooth": [[41530, 1, 1]], "vl_covdet_set_edge_threshold": [[41530, 1, 1]], "vl_covdet_set_first_octav": [[41530, 1, 1]], "vl_covdet_set_laplacian_peak_threshold": [[41530, 1, 1]], "vl_covdet_set_non_extrema_suppression_threshold": [[41530, 1, 1]], "vl_covdet_set_octave_resolut": [[41530, 1, 1]], "vl_covdet_set_peak_threshold": [[41530, 1, 1]], "vl_covdet_set_transpos": [[41530, 1, 1]], "vl_cpu_has_avx": [[41530, 1, 1]], "vl_cpu_has_sse2": [[41530, 1, 1]], "vl_cpu_has_sse3": [[41530, 1, 1]], "vl_destructor": [[41530, 1, 1]], "vl_disable_openmp": [[41530, 1, 1]], "vl_disable_sse2": [[41530, 1, 1]], "vl_disable_thread": [[41530, 1, 1]], "vl_dsift_delet": [[41530, 1, 1]], "dsift": [[41530, 23, 1]], "vl_dsift_get_bound": [[41530, 1, 1]], "vl_dsift_get_descriptor_s": [[41530, 1, 1]], "vl_dsift_get_descriptor": [[41530, 1, 1]], "vl_dsift_get_flat_window": [[41530, 1, 1]], "vl_dsift_get_geometri": [[41530, 1, 1]], "vl_dsift_get_keypoint_num": [[41530, 1, 1]], "vl_dsift_get_keypoint": [[41530, 1, 1]], "vl_dsift_get_step": [[41530, 1, 1]], "vl_dsift_get_window_s": [[41530, 1, 1]], "vl_dsift_new": [[41530, 1, 1]], "vl_dsift_new_bas": [[41530, 1, 1]], "vl_dsift_process": [[41530, 1, 1]], "vl_dsift_set_bound": [[41530, 1, 1]], "vl_dsift_set_flat_window": [[41530, 1, 1]], "vl_dsift_set_geometri": [[41530, 1, 1]], "vl_dsift_set_step": [[41530, 1, 1]], "vl_dsift_set_window_s": [[41530, 1, 1]], "vl_dsift_transpose_descriptor": [[41530, 1, 1]], "vl_e": [[41530, 1, 1]], "vl_enumeration_get": [[41530, 1, 1]], "stringop": [[41530, 28, 1]], "vl_enumeration_get_by_valu": [[41530, 1, 1]], "vl_enumeration_get_casei": [[41530, 1, 1]], "vl_epsilon_d": [[41530, 1, 1]], "vl_epsilon_f": [[41530, 1, 1]], "vl_err_alloc": [[41530, 1, 1]], "vl_err_bad_arg": [[41530, 1, 1]], "vl_err_eof": [[41530, 1, 1]], "vl_err_io": [[41530, 1, 1]], "vl_err_msg_len": [[41530, 1, 1]], "vl_err_no_mor": [[41530, 1, 1]], "vl_err_ok": [[41530, 1, 1]], "vl_err_overflow": [[41530, 1, 1]], "vl_err_pgm_inv_data": [[41530, 1, 1]], "pgm": [[41530, 22, 1]], "vl_err_pgm_inv_head": [[41530, 1, 1]], "vl_err_pgm_inv_meta": [[41530, 1, 1]], "vl_err_pgm_io": [[41530, 1, 1]], "vl_eval_vector_comparison_on_all_pairs_d": [[41530, 1, 1]], "vl_eval_vector_comparison_on_all_pairs_f": [[41530, 1, 1]], "vl_export": [[41530, 1, 1]], "vl_fals": [[41530, 1, 1]], "vl_fast_atan2_d": [[41530, 1, 1]], "vl_fast_atan2_f": [[41530, 1, 1]], "vl_fast_resqrt_d": [[41530, 1, 1]], "vl_fast_resqrt_f": [[41530, 1, 1]], "vl_fast_sqrt_d": [[41530, 1, 1]], "vl_fast_sqrt_f": [[41530, 1, 1]], "vl_fast_sqrt_ui16": [[41530, 1, 1]], "vl_fast_sqrt_ui32": [[41530, 1, 1]], "vl_fast_sqrt_ui64": [[41530, 1, 1]], "vl_fast_sqrt_ui8": [[41530, 1, 1]], "vl_find_local_extrema_2": [[41530, 1, 1]], "vl_find_local_extrema_3": [[41530, 1, 1]], "vl_fisher_encod": [[41530, 1, 1]], "vl_fisher_flag_fast": [[41530, 1, 1]], "vl_fisher_flag_improv": [[41530, 1, 1]], "vl_fisher_flag_norm": [[41530, 1, 1]], "vl_fisher_flag_square_root": [[41530, 1, 1]], "vl_fl_index": [[41530, 1, 1]], "vl_fl_int16": [[41530, 1, 1]], "vl_fl_int32": [[41530, 1, 1]], "vl_fl_int64": [[41530, 1, 1]], "vl_fl_int8": [[41530, 1, 1]], "vl_floor_d": [[41530, 1, 1]], "vl_floor_f": [[41530, 1, 1]], "vl_fmt_index": [[41530, 1, 1]], "vl_fmt_intptr": [[41530, 1, 1]], "vl_fmt_size": [[41530, 1, 1]], "vl_fmt_uindex": [[41530, 1, 1]], "vl_fmt_uintptr": [[41530, 1, 1]], "vl_frametype_disc": [[41530, 1, 1]], "vl_frametype_ellips": [[41530, 1, 1]], "vl_frametype_oriented_disc": [[41530, 1, 1]], "vl_frametype_oriented_ellips": [[41530, 1, 1]], "vl_free": [[41530, 1, 1]], "vl_get_cpu_tim": [[41530, 1, 1]], "vl_get_frame_s": [[41530, 1, 1]], "vl_get_frame_typ": [[41530, 1, 1]], "vl_get_last_error": [[41530, 1, 1]], "vl_get_last_error_messag": [[41530, 1, 1]], "vl_get_max_thread": [[41530, 1, 1]], "vl_get_num_cpu": [[41530, 1, 1]], "vl_get_printf_func": [[41530, 1, 1]], "vl_get_rand": [[41530, 1, 1]], "vl_get_simd_en": [[41530, 1, 1]], "vl_get_stat": [[41530, 1, 1]], "vl_get_thread_limit": [[41530, 1, 1]], "vl_get_thread_specific_st": [[41530, 1, 1]], "vl_get_type_nam": [[41530, 1, 1]], "vl_get_type_s": [[41530, 1, 1]], "vl_get_vector_comparison_function_d": [[41530, 1, 1]], "vl_get_vector_comparison_function_f": [[41530, 1, 1]], "vl_get_vector_comparison_type_nam": [[41530, 1, 1]], "vl_get_version_str": [[41530, 1, 1]], "vl_gmm_cluster": [[41530, 1, 1]], "gmm": [[41530, 71, 1]], "vl_gmm_delet": [[41530, 1, 1]], "vl_gmm_em": [[41530, 1, 1]], "vl_gmm_get_covariance_lower_bound": [[41530, 1, 1]], "vl_gmm_get_covari": [[41530, 1, 1]], "vl_gmm_get_data_typ": [[41530, 1, 1]], "vl_gmm_get_dimens": [[41530, 1, 1]], "vl_gmm_get_initi": [[41530, 1, 1]], "vl_gmm_get_kmeans_init_object": [[41530, 1, 1]], "vl_gmm_get_loglikelihood": [[41530, 1, 1]], "vl_gmm_get_max_num_iter": [[41530, 1, 1]], "vl_gmm_get_mean": [[41530, 1, 1]], "vl_gmm_get_num_clust": [[41530, 1, 1]], "vl_gmm_get_num_data": [[41530, 1, 1]], "vl_gmm_get_num_repetit": [[41530, 1, 1]], "vl_gmm_get_posterior": [[41530, 1, 1]], "vl_gmm_get_prior": [[41530, 1, 1]], "vl_gmm_get_verbos": [[41530, 1, 1]], "vl_gmm_init_with_kmean": [[41530, 1, 1]], "vl_gmm_init_with_rand_data": [[41530, 1, 1]], "vl_gmm_new": [[41530, 1, 1]], "vl_gmm_new_copi": [[41530, 1, 1]], "vl_gmm_reset": [[41530, 1, 1]], "vl_gmm_set_covariance_lower_bound": [[41530, 2, 1]], "vl_gmm_set_covari": [[41530, 1, 1]], "vl_gmm_set_initi": [[41530, 1, 1]], "vl_gmm_set_kmeans_init_object": [[41530, 1, 1]], "vl_gmm_set_max_num_iter": [[41530, 1, 1]], "vl_gmm_set_mean": [[41530, 1, 1]], "vl_gmm_set_num_repetit": [[41530, 1, 1]], "vl_gmm_set_prior": [[41530, 1, 1]], "vl_gmm_set_verbos": [[41530, 1, 1]], "vl_heap_array": [[41530, 1, 1]], "heap": [[41530, 13, 1]], "def": [[41530, 25, 1]], "vl_heap_cmp": [[41530, 1, 1]], "vl_heap_down": [[41530, 1, 1]], "vl_heap_left_child": [[41530, 1, 1]], "vl_heap_par": [[41530, 1, 1]], "vl_heap_pop": [[41530, 1, 1]], "vl_heap_prefix": [[41530, 1, 1]], "vl_heap_push": [[41530, 1, 1]], "vl_heap_right_child": [[41530, 1, 1]], "vl_heap_swap": [[41530, 1, 1]], "vl_heap_typ": [[41530, 1, 1]], "vl_heap_up": [[41530, 1, 1]], "vl_heap_upd": [[41530, 1, 1]], "vl_hikm_copy_subset": [[41530, 1, 1]], "hikmean": [[41530, 27, 1]], "vl_hikm_delet": [[41530, 1, 1]], "vl_hikm_get_depth": [[41530, 1, 1]], "vl_hikm_get_k": [[41530, 1, 1]], "vl_hikm_get_max_nit": [[41530, 1, 1]], "vl_hikm_get_ndim": [[41530, 1, 1]], "vl_hikm_get_root": [[41530, 1, 1]], "vl_hikm_get_verbos": [[41530, 1, 1]], "vl_hikm_init": [[41530, 1, 1]], "vl_hikm_new": [[41530, 1, 1]], "vl_hikm_push": [[41530, 1, 1]], "vl_hikm_set_max_nit": [[41530, 1, 1]], "vl_hikm_set_verbos": [[41530, 1, 1]], "vl_hikm_train": [[41530, 1, 1]], "vl_hog_delet": [[41530, 1, 1]], "vl_hog_extract": [[41530, 1, 1]], "vl_hog_get_dimens": [[41530, 1, 1]], "vl_hog_get_glyph_s": [[41530, 1, 1]], "vl_hog_get_height": [[41530, 1, 1]], "vl_hog_get_permut": [[41530, 1, 1]], "vl_hog_get_use_bilinear_orientation_assign": [[41530, 1, 1]], "vl_hog_get_width": [[41530, 1, 1]], "vl_hog_new": [[41530, 1, 1]], "vl_hog_prepare_buff": [[41530, 1, 1]], "vl_hog_put_imag": [[41530, 1, 1]], "vl_hog_put_polar_field": [[41530, 1, 1]], "vl_hog_rend": [[41530, 1, 1]], "vl_hog_set_use_bilinear_orientation_assign": [[41530, 1, 1]], "vl_homogeneouskernelmap_delet": [[41530, 1, 1]], "homkermap": [[41530, 24, 1]], "vl_homogeneouskernelmap_evaluate_d": [[41530, 1, 1]], "vl_homogeneouskernelmap_evaluate_f": [[41530, 1, 1]], "vl_homogeneouskernelmap_get_dimens": [[41530, 1, 1]], "vl_homogeneouskernelmap_get_kernel_typ": [[41530, 1, 1]], "vl_homogeneouskernelmap_get_ord": [[41530, 1, 1]], "vl_homogeneouskernelmap_get_smooth_spectrum": [[41530, 1, 1]], "vl_homogeneouskernelmap_get_spectrum": [[41530, 1, 1]], "vl_homogeneouskernelmap_get_window_typ": [[41530, 1, 1]], "vl_homogeneouskernelmap_new": [[41530, 1, 1]], "vl_ikm_delet": [[41530, 1, 1]], "ikmean": [[41530, 31, 1]], "vl_ikm_elkan": [[41530, 1, 1]], "vl_ikm_elkan_update_inter_dist": [[41530, 1, 1]], "ikmeans_elkan": [[41530, 4, 1]], "tc": [[41530, 11, 1]], "vl_ikm_get_cent": [[41530, 1, 1]], "vl_ikm_get_k": [[41530, 1, 1]], "vl_ikm_get_max_nit": [[41530, 1, 1]], "vl_ikm_get_ndim": [[41530, 1, 1]], "vl_ikm_get_verbos": [[41530, 1, 1]], "vl_ikm_init": [[41530, 1, 1]], "ikmeans_init": [[41530, 4, 1]], "vl_ikm_init_elkan": [[41530, 1, 1]], "vl_ikm_init_help": [[41530, 1, 1]], "vl_ikm_init_lloyd": [[41530, 1, 1]], "ikmeans_lloyd": [[41530, 3, 1]], "vl_ikm_init_rand": [[41530, 1, 1]], "vl_ikm_init_rand_data": [[41530, 1, 1]], "vl_ikm_lloyd": [[41530, 1, 1]], "vl_ikm_new": [[41530, 1, 1]], "vl_ikm_push": [[41530, 1, 1]], "vl_ikm_push_elkan": [[41530, 1, 1]], "vl_ikm_push_lloyd": [[41530, 1, 1]], "vl_ikm_push_on": [[41530, 1, 1]], "vl_ikm_set_max_nit": [[41530, 1, 1]], "vl_ikm_set_verbos": [[41530, 1, 1]], "vl_ikm_train": [[41530, 1, 1]], "vl_ikm_train_elkan": [[41530, 1, 1]], "vl_ikm_train_lloyd": [[41530, 1, 1]], "vl_ikmacc_t": [[41530, 1, 1]], "vl_image_distance_transform_d": [[41530, 1, 1]], "imopv": [[41530, 18, 1]], "vl_image_distance_transform_f": [[41530, 1, 1]], "vl_imconvcol_vd": [[41530, 1, 1]], "vl_imconvcol_vf": [[41530, 1, 1]], "vl_imconvcoltri_d": [[41530, 1, 1]], "vl_imconvcoltri_f": [[41530, 1, 1]], "vl_imgradient_polar_d": [[41530, 1, 1]], "vl_imgradient_polar_f": [[41530, 1, 1]], "vl_imintegral_d": [[41530, 1, 1]], "vl_imintegral_f": [[41530, 1, 1]], "vl_imintegral_i32": [[41530, 1, 1]], "vl_imintegral_ui32": [[41530, 1, 1]], "vl_imsmooth_d": [[41530, 1, 1]], "vl_imsmooth_f": [[41530, 1, 1]], "vl_index": [[41530, 1, 1]], "vl_infinity_d": [[41530, 2, 1]], "vl_infinity_f": [[41530, 2, 1]], "vl_inlin": [[41530, 1, 1]], "vl_int": [[41530, 1, 1]], "vl_int16": [[41530, 1, 1]], "vl_int16_c": [[41530, 1, 1]], "vl_int32": [[41530, 1, 1]], "vl_int32_c": [[41530, 1, 1]], "vl_int64": [[41530, 1, 1]], "vl_int64_c": [[41530, 1, 1]], "vl_int8": [[41530, 1, 1]], "vl_int8_c": [[41530, 1, 1]], "vl_intptr": [[41530, 1, 1]], "vl_irodrigu": [[41530, 1, 1]], "rodrigu": [[41530, 4, 1]], "vl_is_inf_d": [[41530, 1, 1]], "vl_is_inf_f": [[41530, 1, 1]], "vl_is_nan_d": [[41530, 1, 1]], "vl_is_nan_f": [[41530, 1, 1]], "vl_kdforest_build": [[41530, 1, 1]], "kdtree": [[41530, 41, 1]], "vl_kdforest_delet": [[41530, 1, 1]], "vl_kdforest_get_data_dimens": [[41530, 1, 1]], "vl_kdforest_get_data_typ": [[41530, 1, 1]], "vl_kdforest_get_depth_of_tre": [[41530, 1, 1]], "vl_kdforest_get_max_num_comparison": [[41530, 1, 1]], "vl_kdforest_get_num_nodes_of_tre": [[41530, 1, 1]], "vl_kdforest_get_num_tre": [[41530, 1, 1]], "vl_kdforest_get_thresholding_method": [[41530, 1, 1]], "vl_kdforest_new": [[41530, 1, 1]], "vl_kdforest_new_search": [[41530, 1, 1]], "vl_kdforest_queri": [[41530, 1, 1]], "vl_kdforest_query_recurs": [[41530, 1, 1]], "vl_kdforest_query_with_array": [[41530, 1, 1]], "vl_kdforest_set_max_num_comparison": [[41530, 1, 1]], "vl_kdforest_set_thresholding_method": [[41530, 1, 1]], "vl_kdforestsearcher_delet": [[41530, 1, 1]], "vl_kdforestsearcher_get_forest": [[41530, 1, 1]], "vl_kdforestsearcher_queri": [[41530, 1, 1]], "vl_kdtree_build_recurs": [[41530, 1, 1]], "vl_kdtree_calc_bounds_recurs": [[41530, 1, 1]], "vl_kdtree_compare_index_entri": [[41530, 1, 1]], "vl_kdtree_node_new": [[41530, 1, 1]], "vl_kmeans_clust": [[41530, 1, 1]], "kmean": [[41530, 49, 1]], "vl_kmeans_delet": [[41530, 1, 1]], "vl_kmeans_get_algorithm": [[41530, 1, 1]], "vl_kmeans_get_cent": [[41530, 1, 1]], "vl_kmeans_get_data_typ": [[41530, 1, 1]], "vl_kmeans_get_dimens": [[41530, 1, 1]], "vl_kmeans_get_dist": [[41530, 1, 1]], "vl_kmeans_get_energi": [[41530, 1, 1]], "vl_kmeans_get_initi": [[41530, 1, 1]], "vl_kmeans_get_max_num_comparison": [[41530, 1, 1]], "vl_kmeans_get_max_num_iter": [[41530, 1, 1]], "vl_kmeans_get_min_energy_vari": [[41530, 1, 1]], "vl_kmeans_get_num_cent": [[41530, 1, 1]], "vl_kmeans_get_num_repetit": [[41530, 1, 1]], "vl_kmeans_get_verbos": [[41530, 1, 1]], "vl_kmeans_init_centers_plus_plu": [[41530, 1, 1]], "vl_kmeans_init_centers_with_rand_data": [[41530, 1, 1]], "vl_kmeans_new": [[41530, 1, 1]], "vl_kmeans_new_copi": [[41530, 1, 1]], "vl_kmeans_quant": [[41530, 1, 1]], "vl_kmeans_quantize_ann": [[41530, 1, 1]], "vl_kmeans_refine_cent": [[41530, 1, 1]], "vl_kmeans_reset": [[41530, 1, 1]], "vl_kmeans_set_algorithm": [[41530, 1, 1]], "vl_kmeans_set_cent": [[41530, 1, 1]], "vl_kmeans_set_initi": [[41530, 1, 1]], "vl_kmeans_set_max_num_comparison": [[41530, 1, 1]], "vl_kmeans_set_max_num_iter": [[41530, 1, 1]], "vl_kmeans_set_min_energy_vari": [[41530, 1, 1]], "vl_kmeans_set_num_repetit": [[41530, 1, 1]], "vl_kmeans_set_num_tre": [[41530, 1, 1]], "vl_kmeans_set_verbos": [[41530, 1, 1]], "vl_lbp_delet": [[41530, 1, 1]], "lbp": [[41530, 10, 1]], "vl_lbp_get_dimens": [[41530, 1, 1]], "vl_lbp_new": [[41530, 1, 1]], "vl_lbp_process": [[41530, 1, 1]], "vl_liopdesc_delet": [[41530, 1, 1]], "vl_liopdesc_get_dimens": [[41530, 1, 1]], "vl_liopdesc_get_intensity_threshold": [[41530, 1, 1]], "vl_liopdesc_get_neighbourhood_radiu": [[41530, 1, 1]], "vl_liopdesc_get_num_neighbour": [[41530, 1, 1]], "vl_liopdesc_get_num_spatial_bin": [[41530, 1, 1]], "vl_liopdesc_new": [[41530, 1, 1]], "vl_liopdesc_new_bas": [[41530, 1, 1]], "vl_liopdesc_process": [[41530, 1, 1]], "vl_liopdesc_set_intensity_threshold": [[41530, 1, 1]], "vl_lock_stat": [[41530, 1, 1]], "vl_log2_d": [[41530, 1, 1]], "vl_log2_f": [[41530, 1, 1]], "vl_log_of_2": [[41530, 1, 1]], "vl_malloc": [[41530, 1, 1]], "vl_max": [[41530, 1, 1]], "vl_min": [[41530, 1, 1]], "vl_mod_2pi_d": [[41530, 1, 1]], "vl_mod_2pi_f": [[41530, 1, 1]], "vl_mser_acc": [[41530, 1, 1]], "vl_mser_delet": [[41530, 1, 1]], "vl_mser_ell_fit": [[41530, 1, 1]], "vl_mser_get_delta": [[41530, 1, 1]], "vl_mser_get_el": [[41530, 1, 1]], "vl_mser_get_ell_dof": [[41530, 1, 1]], "vl_mser_get_ell_num": [[41530, 1, 1]], "vl_mser_get_max_area": [[41530, 1, 1]], "vl_mser_get_max_vari": [[41530, 1, 1]], "vl_mser_get_min_area": [[41530, 1, 1]], "vl_mser_get_min_divers": [[41530, 1, 1]], "vl_mser_get_region": [[41530, 1, 1]], "vl_mser_get_regions_num": [[41530, 1, 1]], "vl_mser_get_stat": [[41530, 1, 1]], "vl_mser_new": [[41530, 1, 1]], "vl_mser_pix": [[41530, 1, 1]], "vl_mser_pix_maxv": [[41530, 1, 1]], "vl_mser_process": [[41530, 1, 1]], "vl_mser_set_delta": [[41530, 1, 1]], "vl_mser_set_max_area": [[41530, 1, 1]], "vl_mser_set_max_vari": [[41530, 1, 1]], "vl_mser_set_min_area": [[41530, 1, 1]], "vl_mser_set_min_divers": [[41530, 1, 1]], "vl_mser_void_nod": [[41530, 1, 1]], "vl_nan_d": [[41530, 2, 1]], "vl_nan_f": [[41530, 2, 1]], "vl_os_linux": [[41530, 1, 1]], "vl_os_macosx": [[41530, 1, 1]], "vl_os_win": [[41530, 1, 1]], "vl_os_win64": [[41530, 1, 1]], "vl_pad_by_continu": [[41530, 1, 1]], "vl_pad_by_zero": [[41530, 1, 1]], "vl_pad_mask": [[41530, 1, 1]], "vl_pgm_extract_data": [[41530, 1, 1]], "vl_pgm_extract_head": [[41530, 1, 1]], "vl_pgm_get_bpp": [[41530, 1, 1]], "vl_pgm_get_npixel": [[41530, 1, 1]], "vl_pgm_insert": [[41530, 1, 1]], "vl_pgm_read_new": [[41530, 1, 1]], "vl_pgm_read_new_f": [[41530, 1, 1]], "vl_pgm_write": [[41530, 1, 1]], "vl_pgm_write_f": [[41530, 1, 1]], "vl_pi": [[41530, 1, 1]], "vl_print": [[41530, 1, 1]], "vl_printf": [[41530, 1, 1]], "vl_prot_ascii": [[41530, 1, 1]], "vl_prot_binari": [[41530, 1, 1]], "vl_prot_non": [[41530, 1, 1]], "vl_prot_unknown": [[41530, 1, 1]], "vl_qs_inf": [[41530, 1, 1]], "quickshift": [[41530, 19, 1]], "vl_qs_type": [[41530, 1, 1]], "vl_qsort_array": [[41530, 1, 1]], "qsort": [[41530, 7, 1]], "vl_qsort_cmp": [[41530, 1, 1]], "vl_qsort_prefix": [[41530, 1, 1]], "vl_qsort_sort": [[41530, 1, 1]], "vl_qsort_sort_recurs": [[41530, 1, 1]], "vl_qsort_swap": [[41530, 1, 1]], "vl_qsort_typ": [[41530, 1, 1]], "vl_quickshift_delet": [[41530, 1, 1]], "vl_quickshift_dist": [[41530, 1, 1]], "vl_quickshift_get_dens": [[41530, 1, 1]], "vl_quickshift_get_dist": [[41530, 1, 1]], "vl_quickshift_get_kernel_s": [[41530, 1, 1]], "vl_quickshift_get_max_dist": [[41530, 1, 1]], "vl_quickshift_get_medoid": [[41530, 1, 1]], "vl_quickshift_get_par": [[41530, 1, 1]], "vl_quickshift_inn": [[41530, 1, 1]], "vl_quickshift_new": [[41530, 1, 1]], "vl_quickshift_process": [[41530, 1, 1]], "vl_quickshift_set_kernel_s": [[41530, 1, 1]], "vl_quickshift_set_max_dist": [[41530, 1, 1]], "vl_quickshift_set_medoid": [[41530, 1, 1]], "vl_rand_init": [[41530, 1, 1]], "random": [[41530, 18, 1]], "vl_rand_int31": [[41530, 1, 1]], "vl_rand_int63": [[41530, 1, 1]], "vl_rand_permute_index": [[41530, 1, 1]], "vl_rand_real1": [[41530, 1, 1]], "vl_rand_real2": [[41530, 1, 1]], "vl_rand_real3": [[41530, 1, 1]], "vl_rand_res53": [[41530, 1, 1]], "vl_rand_se": [[41530, 1, 1]], "vl_rand_seed_by_array": [[41530, 1, 1]], "vl_rand_uindex": [[41530, 1, 1]], "vl_rand_uint32": [[41530, 1, 1]], "vl_rand_uint64": [[41530, 1, 1]], "vl_realloc": [[41530, 1, 1]], "vl_refine_local_extreum_2": [[41530, 1, 1]], "vl_refine_local_extreum_3": [[41530, 1, 1]], "vl_rodrigu": [[41530, 1, 1]], "vl_round_d": [[41530, 1, 1]], "vl_round_f": [[41530, 1, 1]], "vl_scalespace_delet": [[41530, 1, 1]], "scalespac": [[41530, 26, 1]], "vl_scalespace_get_default_geometri": [[41530, 1, 1]], "vl_scalespace_get_geometri": [[41530, 1, 1]], "vl_scalespace_get_level": [[41530, 1, 1]], "vl_scalespace_get_level_const": [[41530, 1, 1]], "vl_scalespace_get_level_sigma": [[41530, 1, 1]], "vl_scalespace_get_octave_geometri": [[41530, 1, 1]], "vl_scalespace_new": [[41530, 1, 1]], "vl_scalespace_new_copi": [[41530, 1, 1]], "vl_scalespace_new_shallow_copi": [[41530, 1, 1]], "vl_scalespace_new_with_geometri": [[41530, 1, 1]], "vl_scalespace_put_imag": [[41530, 1, 1]], "vl_scalespacegeometry_is_equ": [[41530, 1, 1]], "vl_set_alloc_func": [[41530, 1, 1]], "vl_set_last_error": [[41530, 1, 1]], "vl_set_num_thread": [[41530, 1, 1]], "vl_set_printf_func": [[41530, 1, 1]], "vl_set_simd_en": [[41530, 1, 1]], "vl_shift_left": [[41530, 1, 1]], "vl_shuffle_array": [[41530, 1, 1]], "shuffl": [[41530, 5, 1]], "vl_shuffle_prefix": [[41530, 1, 1]], "vl_shuffle_shuffl": [[41530, 1, 1]], "vl_shuffle_swap": [[41530, 1, 1]], "vl_shuffle_typ": [[41530, 1, 1]], "vl_sift_bilinear_orient": [[41530, 1, 1]], "vl_sift_calc_keypoint_descriptor": [[41530, 1, 1]], "vl_sift_calc_keypoint_orient": [[41530, 1, 1]], "vl_sift_calc_raw_descriptor": [[41530, 1, 1]], "vl_sift_delet": [[41530, 1, 1]], "vl_sift_detect": [[41530, 1, 1]], "vl_sift_get_edge_thresh": [[41530, 1, 1]], "vl_sift_get_keypoint": [[41530, 1, 1]], "vl_sift_get_magnif": [[41530, 1, 1]], "vl_sift_get_nkeypoint": [[41530, 1, 1]], "vl_sift_get_nlevel": [[41530, 1, 1]], "vl_sift_get_noctav": [[41530, 1, 1]], "vl_sift_get_norm_thresh": [[41530, 1, 1]], "vl_sift_get_octav": [[41530, 1, 1]], "vl_sift_get_octave_first": [[41530, 1, 1]], "vl_sift_get_octave_height": [[41530, 1, 1]], "vl_sift_get_octave_index": [[41530, 1, 1]], "vl_sift_get_octave_width": [[41530, 1, 1]], "vl_sift_get_peak_thresh": [[41530, 1, 1]], "vl_sift_get_window_s": [[41530, 1, 1]], "vl_sift_keypoint_init": [[41530, 1, 1]], "vl_sift_new": [[41530, 1, 1]], "vl_sift_pix": [[41530, 1, 1]], "vl_sift_process_first_octav": [[41530, 1, 1]], "vl_sift_process_next_octav": [[41530, 1, 1]], "vl_sift_set_edge_thresh": [[41530, 1, 1]], "vl_sift_set_magnif": [[41530, 1, 1]], "vl_sift_set_norm_thresh": [[41530, 1, 1]], "vl_sift_set_peak_thresh": [[41530, 1, 1]], "vl_sift_set_window_s": [[41530, 1, 1]], "vl_size": [[41530, 1, 1]], "vl_slic_seg": [[41530, 1, 1]], "vl_small_int": [[41530, 1, 1]], "vl_sqrt_d": [[41530, 1, 1]], "vl_sqrt_f": [[41530, 1, 1]], "vl_static_configuration_to_string_copi": [[41530, 1, 1]], "vl_string_basenam": [[41530, 1, 1]], "vl_string_casei_cmp": [[41530, 1, 1]], "vl_string_copi": [[41530, 1, 1]], "vl_string_copy_sub": [[41530, 1, 1]], "vl_string_find_char_rev": [[41530, 1, 1]], "vl_string_length": [[41530, 1, 1]], "vl_string_parse_protocol": [[41530, 1, 1]], "vl_string_protocol_nam": [[41530, 1, 1]], "vl_string_replace_wildcard": [[41530, 1, 1]], "vl_stringifi": [[41530, 1, 1]], "vl_svm_delet": [[41530, 1, 1]], "vl_svm_get_bia": [[41530, 1, 1]], "vl_svm_get_bias_learning_r": [[41530, 1, 1]], "vl_svm_get_bias_multipli": [[41530, 1, 1]], "vl_svm_get_diagnostic_frequ": [[41530, 1, 1]], "vl_svm_get_dimens": [[41530, 1, 1]], "vl_svm_get_epsilon": [[41530, 1, 1]], "vl_svm_get_iteration_numb": [[41530, 1, 1]], "vl_svm_get_lambda": [[41530, 1, 1]], "vl_svm_get_max_num_iter": [[41530, 1, 1]], "vl_svm_get_model": [[41530, 1, 1]], "vl_svm_get_num_data": [[41530, 1, 1]], "vl_svm_get_scor": [[41530, 1, 1]], "vl_svm_get_solv": [[41530, 1, 1]], "vl_svm_get_statist": [[41530, 1, 1]], "vl_svm_get_weight": [[41530, 1, 1]], "vl_svm_hinge2_conjugate_loss": [[41530, 1, 1]], "vl_svm_hinge2_dca_upd": [[41530, 1, 1]], "vl_svm_hinge2_loss": [[41530, 1, 1]], "vl_svm_hinge2_loss_deriv": [[41530, 1, 1]], "vl_svm_hinge_conjugate_loss": [[41530, 1, 1]], "vl_svm_hinge_dca_upd": [[41530, 1, 1]], "vl_svm_hinge_loss": [[41530, 1, 1]], "vl_svm_hinge_loss_deriv": [[41530, 1, 1]], "vl_svm_l1_conjugate_loss": [[41530, 1, 1]], "vl_svm_l1_dca_upd": [[41530, 1, 1]], "vl_svm_l1_loss": [[41530, 1, 1]], "vl_svm_l1_loss_deriv": [[41530, 1, 1]], "vl_svm_l2_conjugate_loss": [[41530, 1, 1]], "vl_svm_l2_dca_upd": [[41530, 1, 1]], "vl_svm_l2_loss": [[41530, 1, 1]], "vl_svm_l2_loss_deriv": [[41530, 1, 1]], "vl_svm_logistic_conjugate_loss": [[41530, 1, 1]], "vl_svm_logistic_dca_upd": [[41530, 1, 1]], "vl_svm_logistic_loss": [[41530, 1, 1]], "vl_svm_logistic_loss_deriv": [[41530, 1, 1]], "vl_svm_new": [[41530, 1, 1]], "vl_svm_new_with_abstract_data": [[41530, 1, 1]], "vl_svm_new_with_dataset": [[41530, 1, 1]], "vl_svm_set_bia": [[41530, 1, 1]], "vl_svm_set_bias_learning_r": [[41530, 1, 1]], "vl_svm_set_bias_multipli": [[41530, 1, 1]], "vl_svm_set_conjugate_loss_funct": [[41530, 1, 1]], "vl_svm_set_data_funct": [[41530, 1, 1]], "vl_svm_set_dca_update_funct": [[41530, 1, 1]], "vl_svm_set_diagnostic_frequ": [[41530, 1, 1]], "vl_svm_set_diagnostic_funct": [[41530, 1, 1]], "vl_svm_set_epsilon": [[41530, 1, 1]], "vl_svm_set_iteration_numb": [[41530, 1, 1]], "vl_svm_set_lambda": [[41530, 1, 1]], "vl_svm_set_loss": [[41530, 1, 1]], "vl_svm_set_loss_derivative_funct": [[41530, 1, 1]], "vl_svm_set_loss_funct": [[41530, 1, 1]], "vl_svm_set_max_num_iter": [[41530, 1, 1]], "vl_svm_set_model": [[41530, 1, 1]], "vl_svm_set_weight": [[41530, 1, 1]], "vl_svm_train": [[41530, 1, 1]], "vl_svmdataset_delet": [[41530, 1, 1]], "svmdataset": [[41530, 24, 1]], "vl_svmdataset_get_accumulate_funct": [[41530, 1, 1]], "vl_svmdataset_get_data": [[41530, 1, 1]], "vl_svmdataset_get_dimens": [[41530, 1, 1]], "vl_svmdataset_get_homogeneous_kernel_map": [[41530, 1, 1]], "vl_svmdataset_get_inner_product_funct": [[41530, 1, 1]], "vl_svmdataset_get_num_data": [[41530, 1, 1]], "vl_svmdataset_new": [[41530, 1, 1]], "vl_svmdataset_set_homogeneous_kernel_map": [[41530, 1, 1]], "vl_swap_host_big_endianness_2": [[41530, 1, 1]], "vl_swap_host_big_endianness_4": [[41530, 1, 1]], "vl_swap_host_big_endianness_8": [[41530, 1, 1]], "vl_thread_specific_state_delet": [[41530, 1, 1]], "vl_thread_specific_state_new": [[41530, 1, 1]], "vl_threads_posix": [[41530, 1, 1]], "vl_threads_win": [[41530, 1, 1]], "vl_tic": [[41530, 1, 1]], "vl_toc": [[41530, 1, 1]], "vl_transpos": [[41530, 1, 1]], "vl_true": [[41530, 1, 1]], "vl_type_doubl": [[41530, 1, 1]], "vl_type_float": [[41530, 1, 1]], "vl_type_int16": [[41530, 1, 1]], "vl_type_int32": [[41530, 1, 1]], "vl_type_int64": [[41530, 1, 1]], "vl_type_int8": [[41530, 1, 1]], "vl_type_uint16": [[41530, 1, 1]], "vl_type_uint32": [[41530, 1, 1]], "vl_type_uint64": [[41530, 1, 1]], "vl_type_uint8": [[41530, 1, 1]], "vl_uindex": [[41530, 1, 1]], "vl_uint": [[41530, 1, 1]], "vl_uint16": [[41530, 1, 1]], "vl_uint16_c": [[41530, 1, 1]], "vl_uint32": [[41530, 1, 1]], "vl_uint32_c": [[41530, 1, 1]], "vl_uint64": [[41530, 1, 1]], "vl_uint64_c": [[41530, 1, 1]], "vl_uint8": [[41530, 1, 1]], "vl_uint8_c": [[41530, 1, 1]], "vl_uintptr": [[41530, 1, 1]], "vl_unlock_st": [[41530, 1, 1]], "vl_use_matlab_env": [[41530, 1, 1]], "mexutil": [[41530, 23, 1]], "vl_version_str": [[41530, 1, 1]], "vl_vlad_encod": [[41530, 1, 1]], "vl_vlad_flag_normalize_compon": [[41530, 1, 1]], "vl_vlad_flag_normalize_mass": [[41530, 1, 1]], "vl_vlad_flag_square_root": [[41530, 1, 1]], "vl_vlad_flag_unnorm": [[41530, 1, 1]], "vl_xcat": [[41530, 1, 1]], "vl_xcat3": [[41530, 1, 1]], "vl_xcat4": [[41530, 1, 1]], "vl_xcat5": [[41530, 1, 1]], "vl_xstringifi": [[41530, 1, 1]], "vl_yesno": [[41530, 1, 1]], "vlcovdet": [[41530, 1, 1]], "vlcovdetmethod": [[41530, 2, 1]], "vldistancechi2": [[41530, 1, 1]], "vldistancehelling": [[41530, 1, 1]], "vldistancej": [[41530, 1, 1]], "vldistancel1": [[41530, 1, 1]], "vldistancel2": [[41530, 1, 1]], "vldistancemahalanobi": [[41530, 1, 1]], "vldoublevector3comparisonfunct": [[41530, 1, 1]], "vldoublevectorcomparisonfunct": [[41530, 1, 1]], "vlfloatvector3comparisonfunct": [[41530, 1, 1]], "vlfloatvectorcomparisonfunct": [[41530, 1, 1]], "vlframenam": [[41530, 1, 1]], "vlframetyp": [[41530, 2, 1]], "vlgmm": [[41530, 1, 1]], "vlgmmcustom": [[41530, 1, 1]], "vlgmminiti": [[41530, 1, 1]], "vlgmmkmean": [[41530, 1, 1]], "vlgmmrand": [[41530, 1, 1]], "vlhomogeneouskernelchi2": [[41530, 1, 1]], "vlhomogeneouskernelintersect": [[41530, 1, 1]], "vlhomogeneouskernelj": [[41530, 1, 1]], "vlhomogeneouskernelmap": [[41530, 1, 1]], "vlhomogeneouskernelmapwindowrectangular": [[41530, 1, 1]], "vlhomogeneouskernelmapwindowtyp": [[41530, 1, 1]], "vlhomogeneouskernelmapwindowuniform": [[41530, 1, 1]], "vlhomogeneouskerneltyp": [[41530, 1, 1]], "vlikmalgorithm": [[41530, 1, 1]], "vlkdtreethresholdingmethod": [[41530, 1, 1]], "vlkernelchi2": [[41530, 1, 1]], "vlkernelhelling": [[41530, 1, 1]], "vlkernelj": [[41530, 1, 1]], "vlkernell1": [[41530, 1, 1]], "vlkernell2": [[41530, 1, 1]], "vlkmeansalgorithm": [[41530, 1, 1]], "vlkmeansann": [[41530, 1, 1]], "vlkmeanselkan": [[41530, 1, 1]], "vlkmeansiniti": [[41530, 1, 1]], "vlkmeanslloyd": [[41530, 1, 1]], "vlkmeansplusplu": [[41530, 1, 1]], "vlkmeansrandomselect": [[41530, 1, 1]], "vllbpmappingtyp": [[41530, 1, 1]], "vllbpuniform": [[41530, 1, 1]], "vlmxcomparestringsi": [[41530, 1, 1]], "vlmxcomparetostringi": [[41530, 1, 1]], "vlmxcreatearrayfromvlarray": [[41530, 1, 1]], "vlmxcreateplainscalar": [[41530, 1, 1]], "vlmxdecodeenumer": [[41530, 1, 1]], "vlmxenvelopearrayinvlarray": [[41530, 1, 1]], "vlmxerror": [[41530, 1, 1]], "vlmxerrorid": [[41530, 1, 1]], "vlmxisarray": [[41530, 1, 1]], "vlmxisequaltostringi": [[41530, 1, 1]], "vlmxismatrix": [[41530, 1, 1]], "vlmxisofclass": [[41530, 1, 1]], "vlmxisplain": [[41530, 1, 1]], "vlmxisplainmatrix": [[41530, 1, 1]], "vlmxisplainscalar": [[41530, 1, 1]], "vlmxisplainvector": [[41530, 1, 1]], "vlmxisreal": [[41530, 1, 1]], "vlmxisscalar": [[41530, 1, 1]], "vlmxisstr": [[41530, 1, 1]], "vlmxisvector": [[41530, 1, 1]], "vlmxnextopt": [[41530, 1, 1]], "vlmxwarn": [[41530, 1, 1]], "vlsvm": [[41530, 1, 1]], "vlsvmaccumulatefunct": [[41530, 1, 1]], "vlsvmdataset": [[41530, 1, 1]], "vlsvmdcaupdatefunct": [[41530, 1, 1]], "vlsvmdiagnosticfunct": [[41530, 1, 1]], "vlsvminnerproductfunct": [[41530, 1, 1]], "vlsvmlossfunct": [[41530, 1, 1]], "vlsvmlosshing": [[41530, 1, 1]], "vlsvmlosshinge2": [[41530, 1, 1]], "vlsvmlossl1": [[41530, 1, 1]], "vlsvmlossl2": [[41530, 1, 1]], "vlsvmlosslogist": [[41530, 1, 1]], "vlsvmlosstyp": [[41530, 1, 1]], "vlsvmsolvernon": [[41530, 1, 1]], "vlsvmsolversdca": [[41530, 1, 1]], "vlsvmsolversgd": [[41530, 1, 1]], "vlsvmsolverstatu": [[41530, 1, 1]], "vlsvmsolvertyp": [[41530, 1, 1]], "vlsvmstatusconverg": [[41530, 1, 1]], "vlsvmstatusmaxnumiterationsreach": [[41530, 1, 1]], "vlsvmstatustrain": [[41530, 1, 1]], "vlvectorcomparisontyp": [[41530, 1, 1]], "2007": [[41530, 1, 1]], "13": [[41530, 1, 1]], "author": [[41530, 1, 1]], "boffer": [[41531, 2, 2]], "battl": [[41531, 2, 1], [41535, 1, 1]], "prev": [[41531, 1, 1], [41532, 1, 1], [41534, 1, 1], [41535, 2, 1], [41537, 1, 1], [41538, 1, 1], [41539, 1, 1]], "foam": [[41531, 1, 1]], "dive": [[41531, 1, 1]], "up": [[41531, 1, 1], [41532, 1, 1], [41534, 1, 1], [41535, 1, 1], [41536, 1, 1], [41537, 2, 1], [41538, 1, 1], [41539, 1, 1]], "taavi": [[41531, 1, 1]], "s": [[41531, 1, 1], [41532, 1, 1], [41534, 1, 1], [41536, 12, 1]], "tumbl": [[41531, 1, 1]], "birthday": [[41531, 2, 1], [41534, 1, 1]], "next": [[41531, 1, 1], [41532, 1, 1], [41534, 1, 1], [41535, 2, 1], [41536, 1, 1], [41537, 1, 1], [41538, 1, 1], [41539, 1, 1]], "boy": [[41531, 1, 1]], "origin": [[41531, 1, 1], [41532, 1, 1], [41534, 1, 1], [41537, 1, 1], [41538, 1, 1], [41539, 1, 1]], "imag": [[41531, 1, 1], [41532, 1, 1], [41534, 1, 1], [41537, 1, 1], [41538, 1, 1], [41539, 1, 1]], "size": [[41531, 1, 1], [41532, 1, 1], [41534, 1, 1], [41537, 1, 1], [41538, 1, 1], [41539, 1, 1]], "2048x1536": [[41531, 1, 1]], "951kb": [[41531, 1, 1]], "technic": [[41531, 1, 1], [41532, 1, 1], [41534, 1, 1], [41537, 1, 1], [41538, 1, 1], [41539, 1, 1]], "detail": [[41531, 1, 1], [41532, 1, 1], [41534, 1, 1], [41537, 1, 1], [41538, 1, 1], [41539, 1, 1]], "not": [[41531, 1, 1], [41536, 1, 1]], "avail": [[41531, 1, 1]], "ps7": [[41531, 1, 1]], "level": [[41531, 1, 1]], "12": [[41531, 1, 1], [41538, 1, 1]], "1": [[41531, 2, 1], [41532, 3, 1], [41533, 2, 1], [41534, 3, 1], [41537, 1, 1], [41538, 2, 1], [41539, 1, 1]], "245": [[41531, 1, 1]], "usm": [[41531, 1, 1], [41532, 1, 1], [41538, 1, 1]], "30": [[41531, 1, 1], [41532, 1, 1]], "20": [[41531, 1, 1], [41532, 3, 1]], "mani": [[41532, 3, 1], [41536, 1, 1]], "hand": [[41532, 3, 1]], "leed": [[41532, 1, 1]], "unit": [[41532, 1, 1], [41536, 1, 1]], "amanda": [[41532, 3, 1]], "ross": [[41532, 2, 1]], "ho": [[41532, 2, 1]], "palmer": [[41532, 1, 1]], "introduct": [[41532, 1, 1], [41536, 1, 1]], "paisano": [[41532, 1, 1]], "2012": [[41532, 2, 1]], "teeni": [[41532, 1, 1]], "woman": [[41532, 1, 1]], "show": [[41532, 1, 1]], "at": [[41532, 1, 1], [41533, 1, 1], [41536, 7, 1]], "moca": [[41532, 1, 1]], "taken": [[41532, 1, 1], [41534, 1, 1], [41537, 1, 1], [41538, 1, 1], [41539, 1, 1]], "wednesday": [[41532, 1, 1], [41538, 1, 1], [41539, 1, 1]], "juli": [[41532, 1, 1]], "18": [[41532, 1, 1]], "04": [[41532, 1, 1], [41534, 1, 1]], "42": [[41532, 1, 1]], "56pm": [[41532, 1, 1]], "2592x3888": [[41532, 1, 1], [41534, 1, 1]], "2mb": [[41532, 1, 1]], "canon": [[41532, 1, 1], [41534, 1, 1], [41538, 1, 1], [41539, 1, 1]], "eo": [[41532, 1, 1], [41534, 1, 1], [41538, 1, 1], [41539, 1, 1]], "40d": [[41532, 1, 1], [41534, 1, 1]], "f5": [[41532, 1, 1]], "iso": [[41532, 1, 1], [41534, 1, 1], [41537, 1, 1], [41538, 1, 1], [41539, 1, 1]], "200": [[41532, 1, 1], [41538, 1, 1], [41539, 1, 1]], "50mm": [[41532, 1, 1], [41534, 1, 1]], "4": [[41532, 1, 1], [41533, 1, 1], [41534, 2, 1]], "80mm": [[41532, 1, 1], [41534, 1, 1]], "equiv": [[41532, 1, 1], [41534, 1, 1], [41538, 1, 1]], "ps": [[41532, 1, 1], [41534, 1, 1], [41539, 1, 1]], "cs5": [[41532, 1, 1]], "4000": [[41532, 1, 1]], "exp0": [[41532, 1, 1]], "25": [[41532, 1, 1], [41537, 1, 1], [41539, 1, 1]], "b10": [[41532, 1, 1]], "con50": [[41532, 1, 1]], "ls25": [[41532, 1, 1]], "index": [[41533, 2, 2]], "eppstein": [[41533, 2, 2]], "pad": [[41533, 2, 1]], "git": [[41533, 2, 2]], "object": [[41533, 2, 1]], "02": [[41533, 2, 2], [41537, 1, 1]], "parent": [[41533, 1, 1]], "directori": [[41533, 1, 1], [41536, 1, 1]], "0ef3e23c5574508e08843b091cd36956836462": [[41533, 1, 1]], "c74a098165315ec385e95606a1fadfe966dfca": [[41533, 1, 1]], "f5430a07c841601762a263e5481069cae91c57": [[41533, 1, 1]], "apach": [[41533, 1, 1]], "2": [[41533, 1, 1], [41537, 1, 1]], "6": [[41533, 1, 1]], "cento": [[41533, 1, 1]], "openssl": [[41533, 1, 1]], "0": [[41533, 1, 1], [41534, 1, 1], [41537, 1, 1], [41538, 4, 1]], "2k": [[41533, 1, 1]], "fip": [[41533, 1, 1]], "svn": [[41533, 1, 1]], "7": [[41533, 1, 1], [41538, 1, 1]], "14": [[41533, 1, 1]], "server": [[41533, 1, 1]], "www": [[41533, 1, 1]], "ic": [[41533, 1, 1], [41536, 10, 1]], "uci": [[41533, 1, 1], [41536, 8, 1]], "edu": [[41533, 1, 1], [41536, 1, 1]], "port": [[41533, 1, 1]], "80": [[41533, 1, 1]], "aiken": [[41534, 2, 2]], "wii": [[41534, 3, 2]], "timothi": [[41534, 1, 1]], "tenth": [[41534, 1, 1]], "darragh": [[41534, 1, 1]], "drink": [[41534, 1, 1]], "saturday": [[41534, 1, 1]], "februari": [[41534, 1, 1]], "28": [[41534, 1, 1]], "2009": [[41534, 1, 1]], "38": [[41534, 1, 1]], "50pm": [[41534, 1, 1]], "8mb": [[41534, 1, 1]], "100": [[41534, 1, 1], [41537, 1, 1], [41538, 2, 1]], "f1": [[41534, 1, 1]], "800": [[41534, 1, 1], [41537, 1, 1]], "cs2": [[41534, 1, 1]], "6000": [[41534, 1, 1]], "exp1": [[41534, 1, 1]], "sat10": [[41534, 1, 1]], "vista": [[41535, 4, 2]], "verd": [[41535, 4, 1]], "world": [[41535, 2, 2], [41536, 2, 1]], "fair": [[41535, 2, 2]], "intern": [[41535, 1, 1]], "day": [[41535, 1, 1], [41536, 1, 1]], "spring": [[41535, 1, 1]], "2005": [[41535, 1, 1]], "butter": [[41535, 1, 1]], "peter": [[41535, 1, 1]], "rabbit": [[41535, 1, 1]], "cabaret": [[41535, 1, 1]], "click": [[41535, 1, 1]], "ani": [[41535, 1, 1]], "pictur": [[41535, 1, 1]], "for": [[41535, 1, 1], [41536, 8, 1]], "larger": [[41535, 1, 1]], "copi": [[41535, 1, 1]], "in": [[41536, 31, 2]], "news": [[41536, 7, 2]], "donald": [[41536, 6, 2]], "bren": [[41536, 9, 2]], "school": [[41536, 10, 2]], "inform": [[41536, 5, 1]], "comput": [[41536, 23, 1]], "scienc": [[41536, 11, 1]], "dean": [[41536, 1, 1]], "welcom": [[41536, 1, 1]], "fact": [[41536, 1, 1]], "figur": [[41536, 1, 1]], "hall": [[41536, 2, 1]], "visit": [[41536, 2, 1]], "equiti": [[41536, 1, 1]], "divers": [[41536, 1, 1]], "contact": [[41536, 5, 1]], "us": [[41536, 1, 1]], "depart": [[41536, 1, 1]], "informat": [[41536, 2, 1]], "statist": [[41536, 2, 1]], "research": [[41536, 15, 2]], "area": [[41536, 2, 1]], "center": [[41536, 2, 1]], "highlight": [[41536, 2, 1]], "student": [[41536, 13, 1]], "graduat": [[41536, 4, 1]], "prospect": [[41536, 1, 1]], "how": [[41536, 1, 1]], "appli": [[41536, 2, 1]], "program": [[41536, 2, 1]], "studi": [[41536, 2, 1]], "academ": [[41536, 6, 1]], "year": [[41536, 2, 1]], "plan": [[41536, 4, 1]], "form": [[41536, 3, 1]], "polici": [[41536, 11, 1]], "fund": [[41536, 1, 1]], "hous": [[41536, 1, 1]], "campu": [[41536, 1, 1]], "resourc": [[41536, 1, 1]], "handbook": [[41536, 1, 1]], "undergradu": [[41536, 1, 1]], "advis": [[41536, 1, 1]], "cours": [[41536, 2, 1]], "updat": [[41536, 1, 1]], "petit": [[41536, 1, 1]], "major": [[41536, 4, 1]], "minor": [[41536, 1, 1]], "integr": [[41536, 1, 1]], "stand": [[41536, 1, 1]], "add": [[41536, 2, 1]], "drop": [[41536, 1, 1], [41538, 2, 2]], "chang": [[41536, 2, 1]], "option": [[41536, 1, 1]], "coursework": [[41536, 2, 1]], "outsid": [[41536, 1, 1]], "grade": [[41536, 1, 1]], "laptop": [[41536, 1, 1]], "withdraw": [[41536, 1, 1]], "readmiss": [[41536, 1, 1]], "cs": [[41536, 1, 1]], "199": [[41536, 2, 1]], "in4matx": [[41536, 1, 1]], "life": [[41536, 1, 1]], "upcom": [[41536, 1, 1]], "event": [[41536, 6, 1]], "scholarship": [[41536, 1, 1]], "fellowship": [[41536, 1, 1]], "job": [[41536, 2, 1]], "internship": [[41536, 1, 1]], "peopl": [[41536, 1, 1]], "faculti": [[41536, 4, 1]], "staff": [[41536, 2, 1]], "newsroom": [[41536, 1, 1]], "social": [[41536, 3, 1]], "media": [[41536, 7, 1]], "press": [[41536, 2, 1]], "releas": [[41536, 2, 1]], "annual": [[41536, 2, 1]], "report": [[41536, 2, 1]], "get": [[41536, 1, 1]], "involv": [[41536, 1, 1]], "make": [[41536, 3, 1]], "gift": [[41536, 2, 1]], "alumni": [[41536, 2, 1]], "leadership": [[41536, 1, 1]], "council": [[41536, 1, 1]], "corpor": [[41536, 1, 1]], "partner": [[41536, 1, 1]], "sponsor": [[41536, 1, 1]], "project": [[41536, 9, 1]], "product": [[41536, 3, 1]], "develop": [[41536, 10, 1]], "competit": [[41536, 1, 1]], "commun": [[41536, 1, 1]], "octob": [[41536, 1, 1]], "9": [[41536, 1, 2]], "2015": [[41536, 1, 2]], "game": [[41536, 29, 2], [41538, 1, 1]], "changer": [[41536, 2, 2]], "by": [[41536, 9, 2]], "courtney": [[41536, 2, 2]], "hamilton": [[41536, 2, 2]], "scientist": [[41536, 2, 2]], "walt": [[41536, 2, 2]], "scacchi": [[41536, 16, 2]], "testifi": [[41536, 1, 1]], "befor": [[41536, 2, 1]], "california": [[41536, 12, 2]], "assembl": [[41536, 4, 1]], "futur": [[41536, 5, 1]], "potenti": [[41536, 2, 1]], "educ": [[41536, 6, 1]], "workforc": [[41536, 4, 1]], "influenc": [[41536, 1, 1]], "pioneer": [[41536, 1, 1]], "virtual": [[41536, 6, 1]], "realiti": [[41536, 2, 1]], "state": [[41536, 4, 1]], "may": [[41536, 2, 1]], "soon": [[41536, 1, 1]], "har": [[41536, 1, 1]], "opportun": [[41536, 2, 1]], "two": [[41536, 1, 1]], "technolog": [[41536, 2, 1]], "so": [[41536, 1, 1]], "say": [[41536, 6, 1]], "senior": [[41536, 1, 1]], "who": [[41536, 3, 1]], "spoke": [[41536, 2, 1]], "length": [[41536, 1, 1]], "committe": [[41536, 2, 1]], "art": [[41536, 1, 1]], "entertain": [[41536, 3, 1]], "sport": [[41536, 1, 1]], "tourism": [[41536, 1, 1]], "internet": [[41536, 1, 1]], "august": [[41536, 1, 1], [41538, 1, 1]], "director": [[41536, 1, 1]], "institut": [[41536, 1, 1]], "environ": [[41536, 3, 1]], "ivecg": [[41536, 2, 1]], "an": [[41536, 5, 1]], "hear": [[41536, 3, 1]], "titl": [[41536, 1, 1]], "video": [[41536, 3, 1]], "industri": [[41536, 11, 1]], "stay": [[41536, 1, 1]], "top": [[41536, 1, 1]], "held": [[41536, 1, 1]], "lo": [[41536, 1, 1]], "angel": [[41536, 1, 1]], "focus": [[41536, 1, 1]], "bolster": [[41536, 1, 1]], "progress": [[41536, 1, 1]], "sever": [[41536, 2, 1]], "angl": [[41536, 1, 1]], "univers": [[41536, 5, 1]], "we": [[41536, 4, 1]], "re": [[41536, 2, 1]], "veri": [[41536, 2, 1]], "familiar": [[41536, 1, 1]], "as": [[41536, 9, 1]], "our": [[41536, 3, 1]], "core": [[41536, 1, 1]], "mission": [[41536, 1, 1]], "but": [[41536, 2, 1]], "perspect": [[41536, 1, 1]], "govern": [[41536, 1, 1]], "also": [[41536, 4, 1]], "interest": [[41536, 4, 1]], "facilit": [[41536, 1, 1]], "stimul": [[41536, 1, 1]], "socioeconom": [[41536, 1, 1]], "lead": [[41536, 2, 1]], "econom": [[41536, 2, 1]], "benefactor": [[41536, 1, 1]], "hub": [[41536, 1, 1]], "thi": [[41536, 3, 1]], "believ": [[41536, 1, 1]], "uc": [[41536, 4, 1]], "uniqu": [[41536, 1, 1]], "place": [[41536, 1, 1]], "assist": [[41536, 1, 1]], "such": [[41536, 3, 1]], "eighth": [[41536, 1, 1]], "most": [[41536, 1, 1]], "power": [[41536, 1, 1], [41539, 4, 1]], "economi": [[41536, 2, 1]], "which": [[41536, 1, 1]], "more": [[41536, 3, 1]], "than": [[41536, 1, 1]], "400": [[41536, 1, 1], [41538, 1, 1]], "compani": [[41536, 1, 1]], "thrive": [[41536, 1, 1]], "oper": [[41536, 1, 1]], "it": [[41536, 6, 1]], "arm": [[41536, 1, 1]], "onli": [[41536, 2, 1]], "system": [[41536, 2, 1]], "dedic": [[41536, 1, 1]], "entir": [[41536, 2, 1]], "field": [[41536, 1, 1], [41537, 1, 1]], "similarli": [[41536, 1, 1]], "one": [[41536, 3, 1]], "kind": [[41536, 2, 1]], "impact": [[41536, 1, 1]], "irvin": [[41536, 3, 1]], "biggest": [[41536, 1, 1]], "that": [[41536, 7, 1]], "produc": [[41536, 1, 1]], "highli": [[41536, 1, 1]], "can": [[41536, 2, 1]], "help": [[41536, 3, 1]], "sustain": [[41536, 2, 1]], "expand": [[41536, 1, 1]], "orient": [[41536, 1, 1]], "friendli": [[41536, 1, 1]], "refer": [[41536, 1, 1]], "interdisciplinari": [[41536, 1, 1]], "blend": [[41536, 1, 1]], "mathemat": [[41536, 1, 1]], "physic": [[41536, 1, 1]], "film": [[41536, 1, 1]], "combin": [[41536, 1, 1]], "solid": [[41536, 1, 1]], "foundat": [[41536, 2, 1]], "focu": [[41536, 1, 1]], "design": [[41536, 2, 1]], "build": [[41536, 1, 1]], "understand": [[41536, 1, 1]], "other": [[41536, 1, 1]], "interact": [[41536, 2, 1]], "part": [[41536, 1, 1]], "vision": [[41536, 1, 1]], "want": [[41536, 2, 1]], "share": [[41536, 1, 1]], "just": [[41536, 1, 1]], "are": [[41536, 2, 1]], "popular": [[41536, 2, 1]], "be": [[41536, 2, 1]], "or": [[41536, 7, 1]], "new": [[41536, 3, 1]], "busi": [[41536, 1, 1]], "process": [[41536, 2, 1]], "sociocultur": [[41536, 1, 1]], "ve": [[41536, 1, 1]], "seen": [[41536, 1, 1]], "rise": [[41536, 2, 1]], "explain": [[41536, 1, 1]], "versatil": [[41536, 1, 1]], "enabl": [[41536, 2, 1]], "becaus": [[41536, 1, 1]], "they": [[41536, 3, 1]], "what": [[41536, 1, 1]], "call": [[41536, 1, 1]], "quintessenti": [[41536, 1, 1]], "problem": [[41536, 1, 1]], "cut": [[41536, 1, 1]], "across": [[41536, 1, 1]], "includ": [[41536, 1, 1]], "graphic": [[41536, 1, 1]], "databas": [[41536, 1, 1]], "manag": [[41536, 1, 1]], "languag": [[41536, 1, 1]], "processor": [[41536, 1, 1]], "network": [[41536, 1, 1]], "artifici": [[41536, 1, 1]], "intellig": [[41536, 1, 1]], "softwar": [[41536, 1, 1]], "engin": [[41536, 1, 1]], "human": [[41536, 1, 1]], "cooper": [[41536, 1, 1]], "work": [[41536, 1, 1]], "play": [[41536, 1, 1]], "algorithm": [[41536, 1, 1]], "secur": [[41536, 1, 1]], "particip": [[41536, 1, 1]], "both": [[41536, 1, 1]], "academia": [[41536, 1, 1]], "there": [[41536, 2, 1]], "grow": [[41536, 2, 1]], "cultur": [[41536, 1, 1]], "give": [[41536, 1, 1]], "studio": [[41536, 1, 1]], "startup": [[41536, 1, 1]], "ventur": [[41536, 1, 1]], "see": [[41536, 1, 1]], "themselv": [[41536, 1, 1]], "now": [[41536, 1, 1]], "do": [[41536, 1, 1]], "yourself": [[41536, 1, 1]], "path": [[41536, 1, 1]], "will": [[41536, 1, 1]], "those": [[41536, 2, 1]], "effort": [[41536, 2, 1]], "varieti": [[41536, 1, 1]], "way": [[41536, 1, 1]], "space": [[41536, 1, 1]], "mentorship": [[41536, 1, 1]], "investor": [[41536, 1, 1]], "have": [[41536, 1, 1]], "alreadi": [[41536, 1, 1]], "begun": [[41536, 1, 1]], "through": [[41536, 1, 1]], "present": [[41536, 2, 1]], "where": [[41536, 1, 1]], "he": [[41536, 1, 1]], "group": [[41536, 1, 1]], "scale": [[41536, 1, 1]], "intel": [[41536, 2, 1]], "facil": [[41536, 2, 1]], "modifi": [[41536, 1, 1]], "simpl": [[41536, 1, 1]], "unreal": [[41536, 1, 1]], "tournament": [[41536, 1, 1]], "creat": [[41536, 2, 1]], "train": [[41536, 3, 1]], "employe": [[41536, 1, 1]], "manufactur": [[41536, 1, 1]], "becom": [[41536, 2, 1]], "high": [[41536, 1, 1]], "tech": [[41536, 1, 1]], "worker": [[41536, 1, 1]], "need": [[41536, 1, 1]], "smarter": [[41536, 1, 1]], "idea": [[41536, 1, 1]], "smart": [[41536, 1, 1]], "workplac": [[41536, 1, 1]], "anoth": [[41536, 2, 1]], "collabor": [[41536, 2, 1]], "medicin": [[41536, 1, 1]], "base": [[41536, 1, 1]], "workstat": [[41536, 1, 1]], "rehabilit": [[41536, 1, 1]], "stroke": [[41536, 1, 1]], "patient": [[41536, 2, 1]], "while": [[41536, 1, 1]], "ha": [[41536, 1, 1]], "tangibl": [[41536, 1, 1]], "real": [[41536, 1, 1]], "benefit": [[41536, 2, 1]], "note": [[41536, 2, 1]], "medic": [[41536, 1, 1]], "simul": [[41536, 3, 1]], "surgic": [[41536, 1, 1]], "clinic": [[41536, 1, 1]], "current": [[41536, 1, 1]], "market": [[41536, 1, 1]], "took": [[41536, 1, 1]], "stage": [[41536, 1, 1]], "dure": [[41536, 1, 1]], "testimoni": [[41536, 1, 1]], "demonstr": [[41536, 1, 1]], "urban": [[41536, 2, 1]], "rapid": [[41536, 1, 1]], "transit": [[41536, 1, 1]], "uppsala": [[41536, 1, 1]], "sweden": [[41536, 1, 1]], "between": [[41536, 1, 1]], "professor": [[41536, 1, 1]], "crista": [[41536, 1, 1]], "lope": [[41536, 2, 1]], "start": [[41536, 1, 1]], "encitra": [[41536, 1, 1]], "opensimul": [[41536, 2, 1]], "spearhead": [[41536, 1, 1]], "confer": [[41536, 1, 1]], "close": [[41536, 1, 1], [41537, 1, 1]], "remark": [[41536, 1, 1]], "chair": [[41536, 1, 1]], "honor": [[41536, 1, 1]], "ian": [[41536, 1, 1]], "calderon": [[41536, 1, 1]], "prioriti": [[41536, 1, 1]], "should": [[41536, 2, 1]], "invest": [[41536, 1, 1]], "learn": [[41536, 1, 1]], "emerg": [[41536, 1, 1]], "maintain": [[41536, 1, 1]], "advanc": [[41536, 1, 1]], "posit": [[41536, 1, 1]], "nation": [[41536, 1, 1], [41539, 1, 1]], "leader": [[41536, 1, 1]], "well": [[41536, 1, 1]], "sector": [[41536, 1, 1]], "stori": [[41536, 2, 1]], "photo": [[41536, 1, 1]], "paul": [[41536, 1, 1]], "kennedi": [[41536, 1, 1]], "previou": [[41536, 1, 1]], "lose": [[41536, 1, 1]], "weight": [[41536, 1, 1]], "freez": [[41536, 1, 1]], "fat": [[41536, 1, 1]], "off": [[41536, 1, 1]], "ice": [[41536, 1, 1]], "vest": [[41536, 1, 1]], "postdoctor": [[41536, 1, 1]], "scholar": [[41536, 1, 1]], "per": [[41536, 1, 1]], "larsen": [[41536, 1, 1]], "recogn": [[41536, 1, 1]], "darpa": [[41536, 1, 1]], "riser": [[41536, 1, 1]], "calendar": [[41536, 1, 1]], "interview": [[41536, 1, 1]], "matt": [[41536, 2, 1]], "miller": [[41536, 2, 1]], "949": [[41536, 1, 1]], "824": [[41536, 1, 1]], "1562": [[41536, 1, 1]], "via": [[41536, 1, 1]], "email": [[41536, 1, 1]], "tweet": [[41536, 1, 1]], "ucibren": [[41536, 1, 1]], "view": [[41536, 1, 1]], "6210": [[41536, 1, 1]], "ca": [[41536, 1, 1]], "92697": [[41536, 1, 1]], "3425": [[41536, 1, 1]], "homepag": [[41536, 1, 1]], "employ": [[41536, 1, 1]], "intranet": [[41536, 1, 1]], "kay": [[41536, 1, 1]], "famili": [[41536, 1, 1]], "lab": [[41536, 1, 1]], "map": [[41536, 1, 1]], "direct": [[41536, 1, 1]], "access": [[41536, 1, 1]], "statement": [[41536, 1, 1]], "safeti": [[41536, 1, 1]], "procedur": [[41536, 1, 1]], "privaci": [[41536, 1, 1]], "dri": [[41537, 2, 1]], "grass": [[41537, 2, 2]], "cloud": [[41537, 3, 2]], "thistl": [[41537, 2, 1]], "sept": [[41537, 1, 1]], "2001": [[41537, 2, 1]], "sunday": [[41537, 1, 1]], "septemb": [[41537, 1, 1]], "03": [[41537, 1, 1], [41539, 1, 1]], "38pm": [[41537, 1, 1]], "1600x1200": [[41537, 1, 1]], "964kb": [[41537, 1, 1]], "olympu": [[41537, 1, 1]], "c700uz": [[41537, 1, 1]], "f7": [[41537, 1, 1]], "377mm": [[41537, 1, 1]], "ball": [[41538, 2, 2]], "practic": [[41538, 2, 1]], "first": [[41538, 1, 1]], "sara": [[41538, 1, 1]], "kelsey": [[41538, 1, 1]], "franki": [[41538, 1, 1]], "21": [[41538, 1, 1]], "2002": [[41538, 1, 1]], "06": [[41538, 1, 1]], "01": [[41538, 1, 1]], "26pm": [[41538, 1, 1]], "3072x2048": [[41538, 1, 1]], "5mb": [[41538, 1, 1]], "d60": [[41538, 1, 1]], "f11": [[41538, 1, 1]], "70": [[41538, 1, 1]], "200mm": [[41538, 1, 1]], "f2": [[41538, 1, 1]], "8": [[41538, 1, 1]], "4x": [[41538, 1, 1]], "120mm": [[41538, 1, 1]], "192mm": [[41538, 1, 1]], "ps6": [[41538, 1, 1]], "colin": [[41538, 1, 1]], "3": [[41538, 1, 1], [41539, 1, 1]], "120": [[41538, 1, 1]], "180": [[41538, 1, 1]], "255": [[41538, 2, 1]], "5": [[41538, 1, 1]], "d60isor": [[41538, 1, 1]], "low": [[41538, 1, 1]], "possum": [[41539, 4, 2]], "iii": [[41539, 2, 2]], "ii": [[41539, 1, 1]], "sequoia": [[41539, 1, 1]], "monument": [[41539, 1, 1]], "kern": [[41539, 1, 1]], "valley": [[41539, 1, 1]], "iv": [[41539, 1, 1]], "june": [[41539, 1, 1]], "2008": [[41539, 1, 1]], "36": [[41539, 1, 1]], "44pm": [[41539, 1, 1]], "3132x1762": [[41539, 1, 1]], "0mb": [[41539, 1, 1]], "20d": [[41539, 1, 1]], "1000": [[41539, 1, 1]], "f8": [[41539, 1, 1]], "163mm": [[41539, 1, 1]], "crop": [[41539, 1, 1]]}