{"whi": [[49280, 2, 1]], "exclus": [[49280, 3, 1]], "and": [[49280, 2, 2]], "share": [[49280, 3, 1]], "lock": [[49280, 5, 1]], "are": [[49280, 1, 2]], "too": [[49280, 1, 2]], "rigid": [[49280, 1, 2]], "peopl": [[49280, 2, 1]], "often": [[49280, 1, 1]], "forget": [[49280, 2, 1]], "to": [[49280, 7, 2]], "releas": [[49280, 3, 1]], "requir": [[49280, 1, 1]], "an": [[49280, 1, 1]], "administr": [[49280, 1, 1]], "the": [[49280, 3, 2], [49288, 1, 1]], "allow": [[49280, 1, 2]], "use": [[49280, 1, 2]], "out": [[49280, 1, 2]], "of": [[49280, 1, 2], [49281, 2, 2], [49284, 2, 2], [49287, 1, 1]], "band": [[49280, 1, 2]], "commun": [[49280, 1, 1]], "negoti": [[49280, 1, 1]], "access": [[49280, 1, 2]], "resourc": [[49280, 1, 1]], "if": [[49280, 1, 1]], "someon": [[49280, 1, 1]], "a": [[49280, 1, 1], [49286, 1, 1]], "it": [[49280, 1, 1]], "doesn": [[49280, 1, 1]], "t": [[49280, 1, 1]], "hold": [[49280, 1, 1]], "up": [[49280, 1, 1], [49283, 1, 1], [49284, 1, 1], [49286, 1, 1], [49288, 1, 1]], "entir": [[49280, 1, 1]], "group": [[49280, 1, 1]], "previou": [[49280, 1, 1]], "slide": [[49280, 3, 1], [49287, 1, 1]], "next": [[49280, 1, 1], [49283, 1, 1], [49284, 1, 1], [49286, 1, 1], [49288, 1, 1]], "back": [[49280, 1, 1]], "first": [[49280, 1, 1]], "view": [[49280, 1, 1]], "graphic": [[49280, 1, 1]], "version": [[49280, 1, 1]], "index": [[49281, 2, 2]], "minhaenl": [[49281, 2, 2]], "class": [[49281, 2, 2], [49285, 4, 1]], "2015": [[49281, 2, 2]], "cs_171_fall": [[49281, 2, 2]], "draft": [[49281, 2, 2]], "results_7x7_miss": [[49281, 2, 1]], "results_vs_goodai_w7_h7_g0": [[49281, 2, 2]], "coolcatai": [[49281, 2, 2]], "parent": [[49281, 1, 1]], "directori": [[49281, 1, 1]], "main": [[49281, 1, 1], [49285, 4, 1]], "exe_log": [[49281, 1, 1]], "txt": [[49281, 1, 1]], "apach": [[49281, 1, 1]], "2": [[49281, 1, 1], [49283, 1, 1], [49285, 16, 1], [49288, 2, 1]], "4": [[49281, 1, 1], [49283, 1, 1], [49285, 6, 1], [49286, 1, 1]], "6": [[49281, 1, 1], [49284, 1, 1], [49285, 4, 1]], "cento": [[49281, 1, 1]], "openssl": [[49281, 1, 1]], "1": [[49281, 2, 1], [49283, 2, 1], [49284, 1, 1], [49285, 23, 1], [49286, 3, 1], [49288, 2, 1]], "0": [[49281, 1, 1], [49283, 1, 1], [49284, 2, 1], [49285, 14, 1], [49286, 1, 1], [49288, 3, 1]], "2k": [[49281, 1, 1]], "fip": [[49281, 1, 1]], "svn": [[49281, 1, 1]], "7": [[49281, 1, 1], [49285, 1, 1], [49289, 3, 1]], "14": [[49281, 1, 1], [49286, 1, 1], [49288, 1, 1], [49289, 1, 1]], "server": [[49281, 1, 1]], "at": [[49281, 1, 1]], "www": [[49281, 1, 1]], "ic": [[49281, 1, 1]], "uci": [[49281, 1, 1], [49282, 1, 2]], "edu": [[49281, 1, 1]], "port": [[49281, 1, 1]], "80": [[49281, 1, 1]], "game": [[49282, 1, 2], [49285, 4, 1], [49288, 1, 1]], "lab": [[49282, 1, 2]], "165": [[49283, 2, 2]], "prev": [[49283, 1, 1], [49284, 1, 1], [49286, 1, 1], [49288, 1, 1]], "164": [[49283, 1, 1]], "parti": [[49283, 1, 1]], "for": [[49283, 1, 1]], "graduat": [[49283, 1, 1]], "u": [[49283, 1, 1]], "hill": [[49283, 1, 1]], "senior": [[49283, 1, 1]], "166": [[49283, 1, 1]], "katrinka": [[49283, 1, 1]], "motion": [[49283, 1, 1]], "blur": [[49283, 1, 1]], "taken": [[49283, 1, 1], [49284, 1, 1], [49286, 1, 1], [49288, 1, 1]], "sunday": [[49283, 1, 1]], "june": [[49283, 1, 1], [49286, 1, 1]], "17": [[49283, 1, 1], [49289, 2, 1]], "2012": [[49283, 1, 1]], "08": [[49283, 1, 1]], "29": [[49283, 1, 1]], "45pm": [[49283, 1, 1]], "origin": [[49283, 1, 1], [49284, 1, 1], [49286, 1, 1], [49288, 1, 1]], "imag": [[49283, 1, 1], [49284, 1, 1], [49286, 1, 1], [49288, 1, 1]], "size": [[49283, 1, 1], [49284, 1, 1], [49286, 1, 1], [49288, 1, 1]], "2592x3888": [[49283, 1, 1], [49286, 1, 1]], "1mb": [[49283, 1, 1], [49288, 1, 1]], "technic": [[49283, 1, 1], [49284, 1, 1], [49286, 1, 1], [49288, 1, 1]], "detail": [[49283, 1, 1], [49284, 1, 1], [49286, 1, 1], [49288, 1, 1]], "canon": [[49283, 1, 1], [49284, 1, 1], [49286, 1, 1], [49288, 1, 1]], "eo": [[49283, 1, 1], [49284, 1, 1], [49286, 1, 1], [49288, 1, 1]], "40d": [[49283, 1, 1], [49286, 1, 1]], "10": [[49283, 2, 1], [49289, 4, 1]], "f2": [[49283, 1, 1], [49284, 1, 1], [49286, 1, 1], [49288, 1, 1]], "8": [[49283, 1, 1], [49284, 1, 1], [49285, 1, 1], [49288, 1, 1], [49289, 4, 1]], "iso": [[49283, 1, 1], [49284, 1, 1], [49286, 1, 1], [49288, 1, 1]], "1600": [[49283, 1, 1], [49288, 1, 1]], "50mm": [[49283, 1, 1], [49286, 1, 1]], "f": [[49283, 1, 1], [49286, 1, 1]], "80mm": [[49283, 1, 1], [49286, 1, 1]], "equiv": [[49283, 1, 1], [49284, 1, 1], [49286, 1, 1], [49288, 1, 1]], "ps": [[49283, 1, 1], [49286, 1, 1]], "cs5": [[49283, 1, 1]], "3400": [[49283, 1, 1]], "exp0": [[49283, 1, 1]], "5": [[49283, 1, 1], [49285, 7, 1], [49288, 2, 1], [49289, 1, 1]], "con0": [[49283, 1, 1]], "cv": [[49283, 1, 1]], "20": [[49283, 2, 1], [49288, 1, 1]], "crowd": [[49284, 2, 2]], "pumpkin": [[49284, 5, 1]], "diana": [[49284, 1, 1]], "s": [[49284, 1, 1]], "nerdi": [[49284, 1, 1]], "halloween": [[49284, 1, 1]], "all": [[49284, 1, 1]], "four": [[49284, 1, 1]], "friday": [[49284, 1, 1], [49286, 1, 1]], "octob": [[49284, 1, 1]], "31": [[49284, 1, 1]], "2003": [[49284, 1, 1]], "06": [[49284, 1, 1]], "13": [[49284, 1, 1], [49286, 1, 1], [49289, 3, 1]], "40pm": [[49284, 1, 1], [49286, 1, 1]], "3072x2048": [[49284, 1, 1]], "0mb": [[49284, 1, 1]], "d60": [[49284, 1, 1], [49288, 1, 1]], "4s": [[49284, 1, 1]], "f4": [[49284, 1, 1], [49288, 1, 1]], "400": [[49284, 1, 1]], "70": [[49284, 1, 1], [49288, 2, 1]], "200mm": [[49284, 1, 1], [49288, 1, 1]], "130mm": [[49284, 1, 1]], "208mm": [[49284, 1, 1]], "fvu": [[49284, 1, 1]], "sat": [[49284, 1, 1]], "con": [[49284, 1, 1]], "dec": [[49284, 1, 1]], "3": [[49284, 1, 1], [49285, 10, 1]], "found": [[49285, 6, 1]], "boardwidth": [[49285, 1, 1]], "9": [[49285, 1, 1], [49289, 3, 1]], "boardheight": [[49285, 1, 1]], "graviti": [[49285, 1, 1]], "fals": [[49285, 2, 1]], "winningrun": [[49285, 1, 1]], "gui": [[49285, 1, 1]], "onlyteam": [[49285, 1, 1]], "start": [[49285, 1, 1]], "tournament": [[49285, 1, 1]], "with": [[49285, 1, 1], [49286, 1, 1]], "team": [[49285, 1, 1]], "player": [[49285, 26, 1]], "file": [[49285, 4, 1]], "binhtp_phan_21954036_mimi": [[49285, 4, 1]], "src": [[49285, 4, 1]], "exe": [[49285, 4, 1]], "testai": [[49285, 4, 1]], "poorai": [[49285, 8, 1]], "return": [[49285, 22, 1]], "move": [[49285, 22, 1]], "winner": [[49285, 2, 1]], "loser": [[49285, 2, 1]], "15": [[49286, 2, 2], [49288, 1, 1], [49289, 5, 1]], "rehears": [[49286, 1, 1]], "dinner": [[49286, 1, 1]], "16": [[49286, 1, 1]], "julia": [[49286, 1, 1]], "sippi": [[49286, 1, 1]], "cup": [[49286, 1, 1]], "2008": [[49286, 1, 1]], "04": [[49286, 1, 1]], "33": [[49286, 1, 1]], "2mb": [[49286, 1, 1]], "100": [[49286, 1, 1]], "800": [[49286, 1, 1]], "crw": [[49286, 1, 1], [49288, 1, 1]], "3000": [[49286, 1, 1]], "design": [[49287, 1, 2]], "failur": [[49287, 1, 1]], "11": [[49287, 1, 1], [49289, 2, 1]], "12": [[49287, 1, 1], [49289, 2, 1]], "stephani": [[49288, 2, 1]], "home": [[49288, 3, 2]], "sara": [[49288, 1, 1]], "diamond": [[49288, 1, 1]], "in": [[49288, 1, 1]], "rough": [[49288, 1, 1]], "vs": [[49288, 1, 1]], "batbust": [[49288, 1, 1]], "mia": [[49288, 1, 1]], "1st": [[49288, 1, 1]], "saturday": [[49288, 1, 1]], "may": [[49288, 1, 1]], "07": [[49288, 1, 1]], "2005": [[49288, 1, 1]], "09": [[49288, 1, 1]], "58am": [[49288, 1, 1]], "2048x3072": [[49288, 1, 1]], "200": [[49288, 1, 1]], "4x": [[49288, 1, 1]], "145mm": [[49288, 1, 1]], "232mm": [[49288, 1, 1]], "ps7": [[49288, 1, 1]], "5200": [[49288, 1, 1]], "50": [[49288, 1, 1]], "25": [[49288, 2, 1]], "crop": [[49288, 1, 1]], "usm": [[49288, 1, 1]], "c1": [[49289, 1, 1]], "19": [[49289, 2, 1]], "c2": [[49289, 1, 1]]}